credtools/__init__.py
credtools/cli.py
credtools/cojo.py
credtools/constants.py
credtools/credibleset.py
credtools/credtools.py
credtools/ldmatrix.py
credtools/locus.py
credtools/meta.py
credtools/plot.py
credtools/qc.py
credtools/sumstats.py
credtools/utils.py
credtools/bin/SuSiEx
credtools/bin/finemap
credtools/preprocessing/__init__.py
credtools/preprocessing/chunk.py
credtools/preprocessing/munge.py
credtools/preprocessing/prepare.py
credtools/preprocessing/munging/__init__.py
credtools/preprocessing/munging/constants.py
credtools/preprocessing/munging/core.py
credtools/preprocessing/munging/headers.py
credtools/preprocessing/munging/validation.py
credtools/wrappers/RSparsePro.py
credtools/wrappers/__init__.py
credtools/wrappers/abf.py
credtools/wrappers/abf_cojo.py
credtools/wrappers/finemap.py
credtools/wrappers/multisusie.py
credtools/wrappers/multisusie_rss.py
credtools/wrappers/susie.py
credtools/wrappers/susie_rss.py
credtools/wrappers/susiex.py
credtools-0.3.2.dist-info/METADATA
credtools-0.3.2.dist-info/WHEEL
credtools-0.3.2.dist-info/entry_points.txt
credtools-0.3.2.dist-info/licenses/LICENSE
credtools-0.3.2.dist-info/RECORD
