Metadata-Version: 2.4
Name: credtools
Version: 0.3.2
Summary: multi-ancestry fine-mapping pipeline.
Project-URL: Homepage, https://github.com/Jianhua-Wang/credtools
Project-URL: Repository, https://github.com/Jianhua-Wang/credtools
Author-email: Jianhua Wang <jianhua.mert@gmail.com>
License: MIT
License-File: LICENSE
Classifier: Development Status :: 2 - Pre-Alpha
Classifier: Intended Audience :: Developers
Classifier: License :: OSI Approved :: MIT License
Classifier: Natural Language :: English
Classifier: Programming Language :: Python :: 3
Classifier: Programming Language :: Python :: 3.9
Requires-Python: <3.13,>=3.9
Requires-Dist: cojopy==0.1.2
Requires-Dist: matplotlib>=3.9.2
Requires-Dist: numba>=0.60.0
Requires-Dist: numpy>=1.21.2
Requires-Dist: pandas>=1.3.3
Requires-Dist: rich>=12.4.0
Requires-Dist: scikit-learn>=1.5.2
Requires-Dist: scipy>=1.7.3
Requires-Dist: seaborn>=0.11.0
Requires-Dist: tqdm>=4.66.5
Requires-Dist: typer>=0.7.0
Requires-Dist: upsetplot>=0.6.0
Provides-Extra: dev
Requires-Dist: black>=23.9.1; extra == 'dev'
Requires-Dist: bump2version>=1.0.1; extra == 'dev'
Requires-Dist: flake8-docstrings>=1.7.0; extra == 'dev'
Requires-Dist: flake8>=5.1.0; extra == 'dev'
Requires-Dist: isort>=5.12.0; extra == 'dev'
Requires-Dist: jupyter>=1.0.0; extra == 'dev'
Requires-Dist: mkdocs-autorefs>=0.5.0; extra == 'dev'
Requires-Dist: mkdocs-include-markdown-plugin>=6.0.1; extra == 'dev'
Requires-Dist: mkdocs-material-extensions>=1.2; extra == 'dev'
Requires-Dist: mkdocs-material>=9.4.2; extra == 'dev'
Requires-Dist: mkdocs>=1.5.3; extra == 'dev'
Requires-Dist: mkdocstrings-python>=1.7.0; extra == 'dev'
Requires-Dist: mypy>=1.5.1; extra == 'dev'
Requires-Dist: pip>=23.2.1; extra == 'dev'
Requires-Dist: pre-commit>=3.4.0; extra == 'dev'
Requires-Dist: pytest-cov>=4.1.0; extra == 'dev'
Requires-Dist: pytest>=7.4.2; extra == 'dev'
Requires-Dist: toml>=0.10.2; extra == 'dev'
Requires-Dist: tox>=4.11.3; extra == 'dev'
Requires-Dist: twine>=4.0.2; extra == 'dev'
Requires-Dist: virtualenv>=20.24.5; extra == 'dev'
